simple_aws_ssm_parameter_store/__init__.py
simple_aws_ssm_parameter_store/_version.py
simple_aws_ssm_parameter_store/api.py
simple_aws_ssm_parameter_store/client.py
simple_aws_ssm_parameter_store/constants.py
simple_aws_ssm_parameter_store/model.py
simple_aws_ssm_parameter_store/paths.py
simple_aws_ssm_parameter_store/utils.py
simple_aws_ssm_parameter_store/vendor/__init__.py
simple_aws_ssm_parameter_store/vendor/pytest_cov_helper.py
simple_aws_ssm_parameter_store-0.2.3.dist-info/AUTHORS.rst
simple_aws_ssm_parameter_store-0.2.3.dist-info/LICENSE.txt
simple_aws_ssm_parameter_store-0.2.3.dist-info/METADATA
simple_aws_ssm_parameter_store-0.2.3.dist-info/WHEEL
simple_aws_ssm_parameter_store-0.2.3.dist-info/RECORD
